scanimate/__init__.py
scanimate/display.py
scanimate/io.py
scanimate/moire.py
scanimate/scanimate.py
scanimate/version_info.py
scanimate-0.1.1.dist-info/LICENSE
scanimate-0.1.1.dist-info/METADATA
scanimate-0.1.1.dist-info/WHEEL
scanimate-0.1.1.dist-info/entry_points.txt
scanimate-0.1.1.dist-info/top_level.txt
scanimate-0.1.1.dist-info/RECORD
