Metadata-Version: 2.1
Name: scanimate
Version: 0.1.1
Summary: Tiny package for generating static animations, or "scanimations"
Home-page: https://ryanhartzell.github.io/scanimate
Author: Ryan Hartzell
Author-email: scanimate@gmail.com
Maintainer: Ryan Hartzell
Maintainer-email: scanimate@gmail.com
License: MIT
Download-URL: https://github.com/RyanHartzell/scanimate
Keywords: fun imaging-science animation image-processing stem steam art
Platform: Windows
Platform: Linux
Platform: Mac OS-X
Platform: Unix
Classifier: Development Status :: 1 - Planning
Classifier: Intended Audience :: Science/Research
Classifier: Intended Audience :: Education
Classifier: Topic :: Scientific/Engineering
Classifier: Topic :: Scientific/Engineering :: Image Processing
Classifier: Topic :: Scientific/Engineering :: Physics
Classifier: Topic :: Scientific/Engineering :: Information Analysis
Classifier: License :: OSI Approved :: MIT License
Classifier: Programming Language :: Python
Classifier: Programming Language :: Python :: 3
Classifier: Programming Language :: Python :: 3.7
Classifier: Programming Language :: Python :: 3.8
Classifier: Programming Language :: Python :: 3.9
Classifier: Programming Language :: Python :: Implementation :: CPython
Classifier: Operating System :: MacOS :: MacOS X
Classifier: Operating System :: Microsoft :: Windows
Classifier: Operating System :: POSIX
Classifier: Natural Language :: English
Requires-Python: >=3.7.*
Requires-Dist: Pillow (==8.2.0)
Requires-Dist: cycler (==0.10.0)
Requires-Dist: imageio (==2.9.0)
Requires-Dist: kiwisolver (==1.3.1)
Requires-Dist: matplotlib (==3.4.1)
Requires-Dist: numpy (==1.20.2)
Requires-Dist: pyparsing (==2.4.7)
Requires-Dist: python-dateutil (==2.8.1)
Requires-Dist: six (==1.15.0)
Provides-Extra: dev
